electricalwiresizes/__init__.py
electricalwiresizes/basicelecfunc.py
electricalwiresizes/bd.py
electricalwiresizes/changelog.py
electricalwiresizes/dbcircuit.py
electricalwiresizes/dbcircuitcd.py
electricalwiresizes/distributional.py
electricalwiresizes/distributioncu.py
electricalwiresizes/exportcsv.py
electricalwiresizes/graph.py
electricalwiresizes/mbtal.py
electricalwiresizes/mbtcu.py
electricalwiresizes/mbtcustd.py
electricalwiresizes/shortcircuit.py
electricalwiresizes/version.py
ElectricalWireSizes-0.1.31.dist-info/LICENSE
ElectricalWireSizes-0.1.31.dist-info/METADATA
ElectricalWireSizes-0.1.31.dist-info/WHEEL
ElectricalWireSizes-0.1.31.dist-info/top_level.txt
ElectricalWireSizes-0.1.31.dist-info/RECORD
