Metadata-Version: 2.1
Name: ElectricalWireSizes
Version: 0.1.31
Summary: Module for dimensioning copper electrical conductors, feeder conductor and branch circuits 
Home-page: https://electricalwiresizes.org/
Author: Marco Polo Jacome Toss
Author-email: jacometoss@outlook.com
License: GPL-3.0
Project-URL: Documentation, https://pyews.readthedocs.io/
Project-URL: Source, https://github.com/jacometoss/PyEWS
Project-URL: Funding, https://ko-fi.com/jacometoss
Project-URL: Forum, https://k-denveloper.blogspot.com/
Project-URL: Bug Tracker, https://github.com/jacometoss/PyEWS/issues
Project-URL: Course, https://electricalwiresizes/courses
Keywords: electrical,conductor,size,electricalwiresizes,nom-001-sede-2012,branch,feeder,ElectricalWireSizes
Classifier: License :: OSI Approved :: GNU Affero General Public License v3
Classifier: Programming Language :: Python
Classifier: Programming Language :: Python :: 3
Classifier: Programming Language :: Python :: 3.5
Classifier: Programming Language :: Python :: 3.6
Classifier: Programming Language :: Python :: 3.7
Classifier: Programming Language :: Python :: 3.8
Classifier: Programming Language :: Python :: 3.9
Classifier: Programming Language :: Python :: 3.10
Classifier: Programming Language :: Python :: 3.11
Classifier: Programming Language :: Python :: 3.12
Classifier: Topic :: Software Development :: Libraries :: Python Modules
Classifier: Topic :: Scientific/Engineering :: Physics
Classifier: Topic :: Scientific/Engineering :: Mathematics
Classifier: Topic :: Utilities 
Classifier: Operating System :: Microsoft :: Windows
Classifier: Operating System :: POSIX :: Linux
Requires-Python: >=3.5
License-File: LICENSE
Provides-Extra: wheel
Requires-Dist: wheel ; extra == 'wheel'
